{"cipher_text_hex": "b'fe69ab98395e3151962a519300742b563de90b2fd8b9bedf5726cda0082f0cad5ffcfae9955611033f71c7f583ef66e546eed7eb22b7e03d71e9c3c71aa495ac5b9b870c7a1da82a1aa51e175a04a3a2e975f65c35a96baf8fe68f4c43'", "keypad_2": {"e": 6, "n": 2, "s": 8, "se": 9, "ne": 3, "sw": 7, "nw": 1, "w": 4, "c": 5}, "cipher_base64": "U2FsdGVkX1+vupppZksvRf5pq5g5XjFRlipRkwB0K1Y96Qsv2Lm+31cmzaAILwytX/z66ZVWEQM/ccf1g+9m5Ubu1+sit\n+A9cenDxxqklaxbm4cMeh2oKhqlHhdaBKOi6XX2XDWpa6+P5o9MQw==", "game_wheel": {"e": "NEED HEALING", "n": "EMOTE", "s": "ULTIMATE STATUS", "se": "GROUP UP", "ne": "HELLO", "sw": "VOICE LINE", "nw": "THANK", "w": "ACKNOWLEDGE", "c": null}, "card_tours": "- - - -  --- - - ---   - - --- -\n- --- - -  --- - - - --- - -\n- - ---  - - --- - - - ---\n- - - -  --- - - ---   - - --- -\n- --- - -  --- - - - --- - -\n- --- - -  ---       --- - -", "card_numbani_airlines": "---   - - --- - - - ---   - - --- -\n- - --- - -   --- - -  ---  - -\n---   - - --- - - - ---   - - --- -\n---   - - --- - - - ---   - - --- -\n- - --- - -   --- - -  ---  - -\n---   - - --- - - - ---   - - --- -\n- - --- - -   --- - -  ---  - -\n---   - - --- - - - ---   - - --- -\n---   - - --- - - - ---   - - --- -", "card_numbani_travel": "- - - -  --- - - ---   - - --- - - -\n- --- - -  --- - - - --- - -   --- - -\n- - ---  - - --- - - - ---\n- - - -  --- - - ---   - - --- - - - ---  - -\n- --- - -  --- - - - --- - -   --- - - ---\n- --- - -  ---       --- - -   --- - - --- -\n- - ---  - - ---   - - ---", "alphabet": "ABCDEFGHIJKLMNOPQRSTUVWXYZ0123456789", "winston_lexigram": {"e": "friend", "n": "computer", "s": "peanut butter", "se": "open", "ne": "look", "sw": "water", "nw": "hello", "w": "juice", "c": "room"}, "cipher_salt_hex": "b'afba9a69664b2f45'", "directions": {"ne": {"map": "volskaya", "time": 46, "character": "winston"}, "n": {"map": "nepal", "time": 21, "character": "torb"}, "se": {"map": "hollywood", "time": 24, "character": "mccree"}, "e": {"map": "route66", "time": 17, "character": "mercy"}, "s": {"map": "hanamura", "time": 22, "character": "genji"}, "nw": {"map": "kings_row", "time": 47, "character": "tracer"}, "c": {"map": "anubis", "time": 19, "character": "d.va"}, "w": {"map": "gibraltar", "time": 30, "character": "symmetra"}, "sw": {"map": "hollywood", "time": 34, "character": "bastion"}}, "computed_directions_as_keypad_1_by_time": [6, 5, 8, 2, 3, 4, 1, 9, 7], "usernames": ["WNSTN", "SMBRA"], "blizzard_wheel": {"e": "Seoul", "n": "Irvine", "s": "Shanghai", "se": "Hangzhou", "ne": "Austin", "sw": "Taipei", "nw": "Cork", "w": "Versailles", "c": "Blizzard"}, "keypad_1": {"e": 6, "n": 8, "s": 2, "se": 3, "ne": 9, "sw": 1, "nw": 7, "w": 4, "c": 5}, "airline_boards_new": [{"status": "on_time", "flight": "HG 0614", "side": "left", "time": "20:00", "origin": "seoul"}, {"status": "canceled", "flight": "ES 4R41", "side": "left", "time": "21:30", "origin": "moscow"}, {"status": "on_time", "flight": "BF 3264", "side": "left", "time": "22:15", "origin": "cork"}, {"status": "on_time", "flight": "HA 3252", "side": "left", "time": "22:55", "origin": "hong kong"}, {"status": "on_time", "flight": "OL 7215", "side": "left", "time": "24:00", "origin": "buenos aires"}, {"status": "on_time", "flight": "VW A353", "side": "left", "time": "1:05", "origin": "rome"}, {"status": "canceled", "flight": "CQ 4142", "side": "left", "time": "1:20", "origin": "madrid"}, {"status": "on_time", "flight": "SJ 5863", "side": "left", "time": "2:25", "origin": "paris"}, {"status": "on_time", "flight": "KU 4352", "side": "left", "time": "2:35", "origin": "hanamura"}, {"status": "on_time", "flight": "PO 2567", "side": "left", "time": "2:55", "origin": "delhi"}, {"status": "on_time", "flight": "RG 2554", "side": "left", "time": "3:30", "origin": "shanghai"}, {"status": "canceled", "flight": "JG 2564", "side": "left", "time": "3:55", "origin": "frankfurt"}, {"status": "on_time", "flight": "GR 0254", "side": "right", "time": "4:00", "origin": "singapore"}, {"status": "canceled", "flight": "TE 1331", "side": "right", "time": "4:20", "origin": "austin"}, {"status": "on_time", "flight": "SX 0126", "side": "right", "time": "4:10", "origin": "dorado"}, {"status": "on_time", "flight": "EE 2342", "side": "right", "time": "4:45", "origin": "new york"}, {"status": "on_time", "flight": "UT 2543", "side": "right", "time": "5:00", "origin": "san francisco"}, {"status": "on_time", "flight": "KE 7145", "side": "right", "time": "5:20", "origin": "taipei"}, {"status": "on_time", "flight": "DQ 1276", "side": "right", "time": "5:35", "origin": "johannesburg"}, {"status": "on_time", "flight": "AH 8343", "side": "right", "time": "5:55", "origin": "sydney"}, {"status": "on_time", "flight": "CK 1117", "side": "right", "time": "6:30", "origin": "kings row"}, {"status": "on_time", "flight": "GR 3337", "side": "right", "time": "6:40", "origin": "versailles"}, {"status": "on_time", "flight": "AT 3245", "side": "right", "time": "6:55", "origin": "los angeles"}, {"status": "delayed", "flight": "BJ 3567", "side": "right", "time": "7:20", "origin": "irvine"}], "characters": {"symmetra": {"name": "Symmetra"}, "bastion": {"name": "Bastion"}, "d.va": {"name": "D.va", "real_name": "Hana Song"}, "mercy": {"name": "Mercy", "real_name": "Angela Ziegler"}, "tracer": {"name": "Tracer"}, "winston": {"name": "Winston"}, "mccree": {"name": "McCree"}, "torb": {"name": "Torbjorn"}, "genji": {"name": "Genji"}}, "maps": {"kings_row": {"name": "Kings Row"}, "hollywood": {"name": "Hollywood"}, "anubis": {"location": "Egypt", "name": "Anubis"}, "volskaya": {"name": "Volskaya"}, "gibraltar": {"name": "Gibraltar"}, "hanamura": {"name": "Hanamura"}, "nepal": {"location": "Nepal", "name": "Nepal"}}, "airline_boards_original": [{"status": "on_time", "flight": "HG 0614", "side": "left", "time": "20:00", "origin": "seoul"}, {"status": "delayed", "flight": "ES 4R41", "side": "left", "time": "21:30", "origin": "moscow"}, {"status": "on_time", "flight": "BF 3264", "side": "left", "time": "22:15", "origin": "cork"}, {"status": "on_time", "flight": "HA 3252", "side": "left", "time": "22:55", "origin": "hong kong"}, {"status": "on_time", "flight": "OL 7215", "side": "left", "time": "24:00", "origin": "buenos aires"}, {"status": "on_time", "flight": "VW A353", "side": "left", "time": "1:05", "origin": "rome"}, {"status": "canceled", "flight": "CQ 4142", "side": "left", "time": "1:20", "origin": "madrid"}, {"status": "delayed", "flight": "SJ 5863", "side": "left", "time": "2:25", "origin": "paris"}, {"status": "delayed", "flight": "KU 4352", "side": "left", "time": "2:35", "origin": "tokyo"}, {"status": "on_time", "flight": "PO 2567", "side": "left", "time": "2:55", "origin": "delhi"}, {"status": "on_time", "flight": "RG 2554", "side": "left", "time": "3:30", "origin": "shanghai"}, {"status": "canceled", "flight": "JG 2564", "side": "left", "time": "3:55", "origin": "frankfurt"}, {"status": "on_time", "flight": "GR 0254", "side": "right", "time": "4:00", "origin": "london"}, {"status": "canceled", "flight": "TE 1331", "side": "right", "time": "4:20", "origin": "austin"}, {"status": "on_time", "flight": "SX 0126", "side": "right", "time": "4:10", "origin": "mexico city"}, {"status": "delayed", "flight": "EE 2342", "side": "right", "time": "4:45", "origin": "new york"}, {"status": "on_time", "flight": "UT 2543", "side": "right", "time": "5:00", "origin": "san francisco"}, {"status": "on_time", "flight": "KE 7145", "side": "right", "time": "5:20", "origin": "cairo"}, {"status": "on_time", "flight": "DQ 1276", "side": "right", "time": "5:35", "origin": "johannesburg"}, {"status": "on_time", "flight": "AH 8343", "side": "right", "time": "5:55", "origin": "los angeles"}, {"status": "delayed", "flight": "GT 4212", "side": "right", "time": "6:30", "origin": "london"}, {"status": "on_time", "flight": "GR 3337", "side": "right", "time": "6:40", "origin": "versailles"}, {"status": "on_time", "flight": "AT 3245", "side": "right", "time": "6:55", "origin": "los angeles"}, {"status": "delayed", "flight": "BJ 3567", "side": "right", "time": "7:20", "origin": "irvine"}]}
